{
  "name": "stage2_5",
  "description": "Sample bank for stage2_5 (from arcade DTPK)",
  "arcade_rom": "ic9",
  "arcade_offset": 45822208,
  "samples": [
    {
      "id": "stage2_5_s000",
      "wav": "audio/samples/sample_2930.wav",
      "pitch": "C5",
      "loop_start": 1584,
      "loop_end": 1789,
      "format": "16bit"
    },
    {
      "id": "stage2_5_s001",
      "wav": "audio/samples/sample_2931.wav",
      "pitch": "C5",
      "loop_start": 2722,
      "loop_end": 2927,
      "format": "16bit"
    },
    {
      "id": "stage2_5_s002",
      "wav": "audio/samples/sample_2932.wav",
      "pitch": "C5",
      "loop_start": 513,
      "loop_end": 570,
      "format": "16bit"
    },
    {
      "id": "stage2_5_s003",
      "wav": "audio/samples/sample_2933.wav",
      "pitch": "C5",
      "loop_start": 3264,
      "loop_end": 3366,
      "format": "16bit"
    },
    {
      "id": "stage2_5_s004",
      "wav": "audio/samples/sample_2934.wav",
      "pitch": "C5",
      "loop_start": 20736,
      "loop_end": 26218,
      "format": "16bit"
    },
    {
      "id": "stage2_5_s005",
      "wav": "audio/samples/sample_2935.wav",
      "pitch": "C5",
      "loop_start": 0,
      "loop_end": 11161,
      "format": "8bit"
    },
    {
      "id": "stage2_5_s006",
      "wav": "audio/samples/sample_2936.wav",
      "pitch": "C5",
      "loop_start": 2660,
      "loop_end": 2711,
      "format": "16bit"
    },
    {
      "id": "stage2_5_s007",
      "wav": "audio/samples/sample_2937.wav",
      "pitch": "C5",
      "loop_start": 0,
      "loop_end": 11918,
      "format": "8bit"
    },
    {
      "id": "stage2_5_s008",
      "wav": "audio/samples/sample_2938.wav",
      "pitch": "C5",
      "loop_start": 0,
      "loop_end": 15531,
      "format": "8bit"
    },
    {
      "id": "stage2_5_s009",
      "wav": "audio/samples/sample_2939.wav",
      "pitch": "C5",
      "loop_start": 0,
      "loop_end": 10,
      "format": "16bit"
    },
    {
      "id": "stage2_5_s010",
      "wav": "audio/samples/sample_2940.wav",
      "pitch": "C5",
      "loop_start": 0,
      "loop_end": 1586,
      "format": "8bit"
    },
    {
      "id": "stage2_5_s011",
      "wav": "audio/samples/sample_2941.wav",
      "pitch": "C5",
      "loop_start": 0,
      "loop_end": 4926,
      "format": "16bit"
    },
    {
      "id": "stage2_5_s012",
      "wav": "audio/samples/sample_2942.wav",
      "pitch": "C5",
      "loop_start": 0,
      "loop_end": 8190,
      "format": "16bit"
    },
    {
      "id": "stage2_5_s013",
      "wav": "audio/samples/sample_2943.wav",
      "pitch": "C5",
      "loop_start": 0,
      "loop_end": 7838,
      "format": "16bit"
    },
    {
      "id": "stage2_5_s014",
      "wav": "audio/samples/sample_2944.wav",
      "pitch": "C5",
      "loop_start": 2930,
      "loop_end": 4694,
      "format": "16bit"
    },
    {
      "id": "stage2_5_s015",
      "wav": "audio/samples/sample_2945.wav",
      "pitch": "C5",
      "loop_start": 3407,
      "loop_end": 5014,
      "format": "16bit"
    },
    {
      "id": "stage2_5_s016",
      "wav": "audio/samples/sample_2946.wav",
      "pitch": "C5",
      "loop_start": 928,
      "loop_end": 1576,
      "format": "16bit"
    },
    {
      "id": "stage2_5_s017",
      "wav": "audio/samples/sample_2947.wav",
      "pitch": "C5",
      "loop_start": 229,
      "loop_end": 420,
      "format": "16bit"
    },
    {
      "id": "stage2_5_s018",
      "wav": "audio/samples/sample_2948.wav",
      "pitch": "C5",
      "loop_start": 1516,
      "loop_end": 2122,
      "format": "16bit"
    },
    {
      "id": "stage2_5_s019",
      "wav": "audio/samples/sample_2949.wav",
      "pitch": "C5",
      "loop_start": 1482,
      "loop_end": 2344,
      "format": "16bit"
    },
    {
      "id": "stage2_5_s020",
      "wav": "audio/samples/sample_2950.wav",
      "pitch": "C5",
      "loop_start": 2701,
      "loop_end": 4381,
      "format": "16bit"
    },
    {
      "id": "stage2_5_s021",
      "wav": "audio/samples/sample_2951.wav",
      "pitch": "C5",
      "loop_start": 2862,
      "loop_end": 4016,
      "format": "16bit"
    },
    {
      "id": "stage2_5_s022",
      "wav": "audio/samples/sample_2952.wav",
      "pitch": "C5",
      "loop_start": 0,
      "loop_end": 2214,
      "format": "16bit"
    },
    {
      "id": "stage2_5_s023",
      "wav": "audio/samples/sample_2953.wav",
      "pitch": "C5",
      "loop_start": 1855,
      "loop_end": 2428,
      "format": "16bit"
    },
    {
      "id": "stage2_5_s024",
      "wav": "audio/samples/sample_2954.wav",
      "pitch": "C5",
      "loop_start": 0,
      "loop_end": 2410,
      "format": "16bit"
    },
    {
      "id": "stage2_5_s025",
      "wav": "audio/samples/sample_2955.wav",
      "pitch": "C5",
      "loop_start": 11200,
      "loop_end": 12545,
      "format": "16bit"
    },
    {
      "id": "stage2_5_s026",
      "wav": "audio/samples/sample_2956.wav",
      "pitch": "C5",
      "loop_start": 21246,
      "loop_end": 24512,
      "format": "16bit"
    },
    {
      "id": "stage2_5_s027",
      "wav": "audio/samples/sample_2957.wav",
      "pitch": "C5",
      "loop_start": 2495,
      "loop_end": 3918,
      "format": "16bit"
    },
    {
      "id": "stage2_5_s028",
      "wav": "audio/samples/sample_2958.wav",
      "pitch": "C5",
      "loop_start": 0,
      "loop_end": 2742,
      "format": "16bit"
    },
    {
      "id": "stage2_5_s029",
      "wav": "audio/samples/sample_2959.wav",
      "pitch": "C5",
      "loop_start": 2350,
      "loop_end": 2808,
      "format": "16bit"
    },
    {
      "id": "stage2_5_s030",
      "wav": "audio/samples/sample_2960.wav",
      "pitch": "C5",
      "loop_start": 0,
      "loop_end": 7038,
      "format": "16bit"
    },
    {
      "id": "stage2_5_s031",
      "wav": "audio/samples/sample_2961.wav",
      "pitch": "C5",
      "loop_start": 0,
      "loop_end": 4714,
      "format": "16bit"
    },
    {
      "id": "stage2_5_s032",
      "wav": "audio/samples/sample_2962.wav",
      "pitch": "C5",
      "loop_start": 4787,
      "loop_end": 5286,
      "format": "16bit"
    },
    {
      "id": "stage2_5_s033",
      "wav": "audio/samples/sample_2963.wav",
      "pitch": "C5",
      "loop_start": 0,
      "loop_end": 3726,
      "format": "16bit"
    },
    {
      "id": "stage2_5_s034",
      "wav": "audio/samples/sample_2964.wav",
      "pitch": "C5",
      "loop_start": 0,
      "loop_end": 30194,
      "format": "16bit"
    },
    {
      "id": "stage2_5_s035",
      "wav": "audio/samples/sample_2965.wav",
      "pitch": "C5",
      "loop_start": 0,
      "loop_end": 3934,
      "format": "16bit"
    },
    {
      "id": "stage2_5_s036",
      "wav": "audio/samples/sample_2966.wav",
      "pitch": "C5",
      "loop_start": 0,
      "loop_end": 2130,
      "format": "16bit"
    },
    {
      "id": "stage2_5_s037",
      "wav": "audio/samples/sample_2967.wav",
      "pitch": "C5",
      "loop_start": 0,
      "loop_end": 3984,
      "format": "16bit"
    },
    {
      "id": "stage2_5_s038",
      "wav": "audio/samples/sample_2968.wav",
      "pitch": "C5",
      "loop_start": 0,
      "loop_end": 4506,
      "format": "16bit"
    },
    {
      "id": "stage2_5_s039",
      "wav": "audio/samples/sample_2969.wav",
      "pitch": "C5",
      "loop_start": 0,
      "loop_end": 3390,
      "format": "16bit"
    },
    {
      "id": "stage2_5_s040",
      "wav": "audio/samples/sample_2970.wav",
      "pitch": "C5",
      "loop_start": 3759,
      "loop_end": 4419,
      "format": "16bit"
    },
    {
      "id": "stage2_5_s041",
      "wav": "audio/samples/sample_2971.wav",
      "pitch": "C5",
      "loop_start": 2162,
      "loop_end": 3134,
      "format": "16bit"
    },
    {
      "id": "stage2_5_s042",
      "wav": "audio/samples/sample_2972.wav",
      "pitch": "C5",
      "loop_start": 0,
      "loop_end": 33086,
      "format": "16bit"
    },
    {
      "id": "stage2_5_s043",
      "wav": "audio/samples/sample_2973.wav",
      "pitch": "C5",
      "loop_start": 7002,
      "loop_end": 9323,
      "format": "16bit"
    },
    {
      "id": "stage2_5_s044",
      "wav": "audio/samples/sample_2974.wav",
      "pitch": "C5",
      "loop_start": 0,
      "loop_end": 10206,
      "format": "16bit"
    },
    {
      "id": "stage2_5_s045",
      "wav": "audio/samples/sample_2975.wav",
      "pitch": "C5",
      "loop_start": 2668,
      "loop_end": 7132,
      "format": "16bit"
    },
    {
      "id": "stage2_5_s046",
      "wav": "audio/samples/sample_2976.wav",
      "pitch": "C5",
      "loop_start": 0,
      "loop_end": 1114,
      "format": "16bit"
    },
    {
      "id": "stage2_5_s047",
      "wav": "audio/samples/sample_2977.wav",
      "pitch": "C5",
      "loop_start": 0,
      "loop_end": 23423,
      "format": "16bit"
    },
    {
      "id": "stage2_5_s048",
      "wav": "audio/samples/sample_2978.wav",
      "pitch": "C5",
      "loop_start": 0,
      "loop_end": 23483,
      "format": "16bit"
    },
    {
      "id": "stage2_5_s049",
      "wav": "audio/samples/sample_2979.wav",
      "pitch": "C5",
      "loop_start": 0,
      "loop_end": 23427,
      "format": "16bit"
    },
    {
      "id": "stage2_5_s050",
      "wav": "audio/samples/sample_2980.wav",
      "pitch": "C5",
      "loop_start": 0,
      "loop_end": 23415,
      "format": "16bit"
    },
    {
      "id": "stage2_5_s051",
      "wav": "audio/samples/sample_2981.wav",
      "pitch": "C5",
      "loop_start": 0,
      "loop_end": 23425,
      "format": "16bit"
    },
    {
      "id": "stage2_5_s052",
      "wav": "audio/samples/sample_2982.wav",
      "pitch": "C5",
      "loop_start": 0,
      "loop_end": 7874,
      "format": "16bit"
    },
    {
      "id": "stage2_5_s053",
      "wav": "audio/samples/sample_2983.wav",
      "pitch": "C5",
      "loop_start": 0,
      "loop_end": 7796,
      "format": "16bit"
    },
    {
      "id": "stage2_5_s054",
      "wav": "audio/samples/sample_2984.wav",
      "pitch": "C5",
      "loop_start": 0,
      "loop_end": 7875,
      "format": "16bit"
    },
    {
      "id": "stage2_5_s055",
      "wav": "audio/samples/sample_2985.wav",
      "pitch": "C5",
      "loop_start": 0,
      "loop_end": 7869,
      "format": "16bit"
    },
    {
      "id": "stage2_5_s056",
      "wav": "audio/samples/sample_2986.wav",
      "pitch": "C5",
      "loop_start": 0,
      "loop_end": 5844,
      "format": "16bit"
    },
    {
      "id": "stage2_5_s057",
      "wav": "audio/samples/sample_2987.wav",
      "pitch": "C5",
      "loop_start": 0,
      "loop_end": 13598,
      "format": "16bit"
    },
    {
      "id": "stage2_5_s058",
      "wav": "audio/samples/sample_2988.wav",
      "pitch": "C5",
      "loop_start": 0,
      "loop_end": 9854,
      "format": "16bit"
    },
    {
      "id": "stage2_5_s059",
      "wav": "audio/samples/sample_2989.wav",
      "pitch": "C5",
      "loop_start": 0,
      "loop_end": 20274,
      "format": "16bit"
    },
    {
      "id": "stage2_5_s060",
      "wav": "audio/samples/sample_2990.wav",
      "pitch": "C5",
      "loop_start": 0,
      "loop_end": 34046,
      "format": "16bit"
    },
    {
      "id": "stage2_5_s061",
      "wav": "audio/samples/sample_2991.wav",
      "pitch": "C5",
      "loop_start": 0,
      "loop_end": 12486,
      "format": "16bit"
    },
    {
      "id": "stage2_5_s062",
      "wav": "audio/samples/sample_2992.wav",
      "pitch": "C5",
      "loop_start": 3036,
      "loop_end": 3506,
      "format": "16bit"
    },
    {
      "id": "stage2_5_s063",
      "wav": "audio/samples/sample_2993.wav",
      "pitch": "C5",
      "loop_start": 0,
      "loop_end": 2902,
      "format": "16bit"
    },
    {
      "id": "stage2_5_s064",
      "wav": "audio/samples/sample_2994.wav",
      "pitch": "C5",
      "loop_start": 0,
      "loop_end": 1310,
      "format": "16bit"
    },
    {
      "id": "stage2_5_s065",
      "wav": "audio/samples/sample_2995.wav",
      "pitch": "C5",
      "loop_start": 0,
      "loop_end": 17978,
      "format": "8bit"
    },
    {
      "id": "stage2_5_s066",
      "wav": "audio/samples/sample_2996.wav",
      "pitch": "C5",
      "loop_start": 0,
      "loop_end": 1050,
      "format": "8bit"
    },
    {
      "id": "stage2_5_s067",
      "wav": "audio/samples/sample_2997.wav",
      "pitch": "C5",
      "loop_start": 4016,
      "loop_end": 5169,
      "format": "8bit"
    },
    {
      "id": "stage2_5_s068",
      "wav": "audio/samples/sample_2998.wav",
      "pitch": "C5",
      "loop_start": 0,
      "loop_end": 516,
      "format": "8bit"
    },
    {
      "id": "stage2_5_s069",
      "wav": "audio/samples/sample_2999.wav",
      "pitch": "C5",
      "loop_start": 0,
      "loop_end": 2456,
      "format": "16bit"
    },
    {
      "id": "stage2_5_s070",
      "wav": "audio/samples/sample_3000.wav",
      "pitch": "C5",
      "loop_start": 0,
      "loop_end": 2262,
      "format": "16bit"
    },
    {
      "id": "stage2_5_s071",
      "wav": "audio/samples/sample_3001.wav",
      "pitch": "C5",
      "loop_start": 0,
      "loop_end": 1814,
      "format": "16bit"
    },
    {
      "id": "stage2_5_s072",
      "wav": "audio/samples/sample_3002.wav",
      "pitch": "C5",
      "loop_start": 0,
      "loop_end": 3102,
      "format": "16bit"
    },
    {
      "id": "stage2_5_s073",
      "wav": "audio/samples/sample_3003.wav",
      "pitch": "C5",
      "loop_start": 0,
      "loop_end": 15946,
      "format": "16bit"
    },
    {
      "id": "stage2_5_s074",
      "wav": "audio/samples/sample_3004.wav",
      "pitch": "C5",
      "loop_start": 0,
      "loop_end": 13310,
      "format": "16bit"
    },
    {
      "id": "stage2_5_s075",
      "wav": "audio/samples/sample_3005.wav",
      "pitch": "C5",
      "loop_start": 0,
      "loop_end": 15735,
      "format": "16bit"
    },
    {
      "id": "stage2_5_s076",
      "wav": "audio/samples/sample_3006.wav",
      "pitch": "C5",
      "loop_start": 0,
      "loop_end": 15594,
      "format": "16bit"
    },
    {
      "id": "stage2_5_s077",
      "wav": "audio/samples/sample_3007.wav",
      "pitch": "C5",
      "loop_start": 0,
      "loop_end": 16153,
      "format": "16bit"
    },
    {
      "id": "stage2_5_s078",
      "wav": "audio/samples/sample_3008.wav",
      "pitch": "C5",
      "loop_start": 0,
      "loop_end": 11488,
      "format": "16bit"
    },
    {
      "id": "stage2_5_s079",
      "wav": "audio/samples/sample_3009.wav",
      "pitch": "C5",
      "loop_start": 7234,
      "loop_end": 13376,
      "format": "16bit"
    },
    {
      "id": "stage2_5_s080",
      "wav": "audio/samples/sample_3010.wav",
      "pitch": "C5",
      "loop_start": 0,
      "loop_end": 15328,
      "format": "16bit"
    },
    {
      "id": "stage2_5_s081",
      "wav": "audio/samples/sample_3011.wav",
      "pitch": "C5",
      "loop_start": 0,
      "loop_end": 10113,
      "format": "16bit"
    },
    {
      "id": "stage2_5_s082",
      "wav": "audio/samples/sample_3012.wav",
      "pitch": "C5",
      "loop_start": 0,
      "loop_end": 13504,
      "format": "16bit"
    },
    {
      "id": "stage2_5_s083",
      "wav": "audio/samples/sample_3013.wav",
      "pitch": "C5",
      "loop_start": 0,
      "loop_end": 14034,
      "format": "16bit"
    },
    {
      "id": "stage2_5_s084",
      "wav": "audio/samples/sample_3014.wav",
      "pitch": "C5",
      "loop_start": 0,
      "loop_end": 16348,
      "format": "16bit"
    },
    {
      "id": "stage2_5_s085",
      "wav": "audio/samples/sample_3015.wav",
      "pitch": "C5",
      "loop_start": 0,
      "loop_end": 9850,
      "format": "16bit"
    },
    {
      "id": "stage2_5_s086",
      "wav": "audio/samples/sample_3016.wav",
      "pitch": "C5",
      "loop_start": 0,
      "loop_end": 13269,
      "format": "16bit"
    },
    {
      "id": "stage2_5_s087",
      "wav": "audio/samples/sample_3017.wav",
      "pitch": "C5",
      "loop_start": 0,
      "loop_end": 10234,
      "format": "16bit"
    },
    {
      "id": "stage2_5_s088",
      "wav": "audio/samples/sample_3018.wav",
      "pitch": "C5",
      "loop_start": 0,
      "loop_end": 16808,
      "format": "16bit"
    },
    {
      "id": "stage2_5_s089",
      "wav": "audio/samples/sample_3019.wav",
      "pitch": "C5",
      "loop_start": 0,
      "loop_end": 27644,
      "format": "16bit"
    },
    {
      "id": "stage2_5_s090",
      "wav": "audio/samples/sample_3020.wav",
      "pitch": "C5",
      "loop_start": 0,
      "loop_end": 32692,
      "format": "16bit"
    },
    {
      "id": "stage2_5_s091",
      "wav": "audio/samples/sample_3021.wav",
      "pitch": "C5",
      "loop_start": 0,
      "loop_end": 16169,
      "format": "16bit"
    },
    {
      "id": "stage2_5_s092",
      "wav": "audio/samples/sample_3022.wav",
      "pitch": "C5",
      "loop_start": 0,
      "loop_end": 30427,
      "format": "16bit"
    },
    {
      "id": "stage2_5_s093",
      "wav": "audio/samples/sample_3023.wav",
      "pitch": "C5",
      "loop_start": 0,
      "loop_end": 13255,
      "format": "16bit"
    },
    {
      "id": "stage2_5_s094",
      "wav": "audio/samples/sample_3024.wav",
      "pitch": "C5",
      "loop_start": 0,
      "loop_end": 32724,
      "format": "16bit"
    },
    {
      "id": "stage2_5_s095",
      "wav": "audio/samples/sample_3025.wav",
      "pitch": "C5",
      "loop_start": 0,
      "loop_end": 16368,
      "format": "16bit"
    },
    {
      "id": "stage2_5_s096",
      "wav": "audio/samples/sample_3026.wav",
      "pitch": "C5",
      "loop_start": 0,
      "loop_end": 13246,
      "format": "16bit"
    },
    {
      "id": "stage2_5_s097",
      "wav": "audio/samples/sample_3027.wav",
      "pitch": "C5",
      "loop_start": 0,
      "loop_end": 12193,
      "format": "16bit"
    },
    {
      "id": "stage2_5_s098",
      "wav": "audio/samples/sample_3028.wav",
      "pitch": "C5",
      "loop_start": 0,
      "loop_end": 15448,
      "format": "16bit"
    },
    {
      "id": "stage2_5_s099",
      "wav": "audio/samples/sample_3029.wav",
      "pitch": "C5",
      "loop_start": 0,
      "loop_end": 12507,
      "format": "16bit"
    },
    {
      "id": "stage2_5_s100",
      "wav": "audio/samples/sample_3030.wav",
      "pitch": "C5",
      "loop_start": 0,
      "loop_end": 15969,
      "format": "16bit"
    },
    {
      "id": "stage2_5_s101",
      "wav": "audio/samples/sample_3031.wav",
      "pitch": "C5",
      "loop_start": 0,
      "loop_end": 7101,
      "format": "16bit"
    },
    {
      "id": "stage2_5_s102",
      "wav": "audio/samples/sample_3032.wav",
      "pitch": "C5",
      "loop_start": 0,
      "loop_end": 13728,
      "format": "16bit"
    },
    {
      "id": "stage2_5_s103",
      "wav": "audio/samples/sample_3033.wav",
      "pitch": "C5",
      "loop_start": 0,
      "loop_end": 12904,
      "format": "16bit"
    },
    {
      "id": "stage2_5_s104",
      "wav": "audio/samples/sample_3034.wav",
      "pitch": "C5",
      "loop_start": 0,
      "loop_end": 6346,
      "format": "16bit"
    },
    {
      "id": "stage2_5_s105",
      "wav": "audio/samples/sample_3035.wav",
      "pitch": "C5",
      "loop_start": 0,
      "loop_end": 6564,
      "format": "16bit"
    },
    {
      "id": "stage2_5_s106",
      "wav": "audio/samples/sample_3036.wav",
      "pitch": "C5",
      "loop_start": 0,
      "loop_end": 9360,
      "format": "16bit"
    },
    {
      "id": "stage2_5_s107",
      "wav": "audio/samples/sample_3037.wav",
      "pitch": "C5",
      "loop_start": 0,
      "loop_end": 13358,
      "format": "16bit"
    },
    {
      "id": "stage2_5_s108",
      "wav": "audio/samples/sample_3038.wav",
      "pitch": "C5",
      "loop_start": 0,
      "loop_end": 6663,
      "format": "16bit"
    },
    {
      "id": "stage2_5_s109",
      "wav": "audio/samples/sample_3039.wav",
      "pitch": "C5",
      "loop_start": 0,
      "loop_end": 10304,
      "format": "16bit"
    },
    {
      "id": "stage2_5_s110",
      "wav": "audio/samples/sample_3040.wav",
      "pitch": "C5",
      "loop_start": 0,
      "loop_end": 24582,
      "format": "16bit"
    },
    {
      "id": "stage2_5_s111",
      "wav": "audio/samples/sample_3041.wav",
      "pitch": "C5",
      "loop_start": 0,
      "loop_end": 16027,
      "format": "16bit"
    },
    {
      "id": "stage2_5_s112",
      "wav": "audio/samples/sample_3042.wav",
      "pitch": "C5",
      "loop_start": 0,
      "loop_end": 14120,
      "format": "16bit"
    },
    {
      "id": "stage2_5_s113",
      "wav": "audio/samples/sample_3043.wav",
      "pitch": "C5",
      "loop_start": 0,
      "loop_end": 5556,
      "format": "16bit"
    },
    {
      "id": "stage2_5_s114",
      "wav": "audio/samples/sample_3044.wav",
      "pitch": "C5",
      "loop_start": 0,
      "loop_end": 13417,
      "format": "16bit"
    },
    {
      "id": "stage2_5_s115",
      "wav": "audio/samples/sample_3045.wav",
      "pitch": "C5",
      "loop_start": 0,
      "loop_end": 13064,
      "format": "16bit"
    },
    {
      "id": "stage2_5_s116",
      "wav": "audio/samples/sample_3046.wav",
      "pitch": "C5",
      "loop_start": 0,
      "loop_end": 13144,
      "format": "16bit"
    },
    {
      "id": "stage2_5_s117",
      "wav": "audio/samples/sample_3047.wav",
      "pitch": "C5",
      "loop_start": 0,
      "loop_end": 5294,
      "format": "16bit"
    },
    {
      "id": "stage2_5_s118",
      "wav": "audio/samples/sample_3048.wav",
      "pitch": "C5",
      "loop_start": 0,
      "loop_end": 5318,
      "format": "16bit"
    },
    {
      "id": "stage2_5_s119",
      "wav": "audio/samples/sample_3049.wav",
      "pitch": "C5",
      "loop_start": 0,
      "loop_end": 6398,
      "format": "16bit"
    },
    {
      "id": "stage2_5_s120",
      "wav": "audio/samples/sample_3050.wav",
      "pitch": "C5",
      "loop_start": 0,
      "loop_end": 5838,
      "format": "16bit"
    },
    {
      "id": "stage2_5_s121",
      "wav": "audio/samples/sample_3051.wav",
      "pitch": "C5",
      "loop_start": 0,
      "loop_end": 7742,
      "format": "16bit"
    },
    {
      "id": "stage2_5_s122",
      "wav": "audio/samples/sample_3052.wav",
      "pitch": "C5",
      "loop_start": 0,
      "loop_end": 7079,
      "format": "16bit"
    },
    {
      "id": "stage2_5_s123",
      "wav": "audio/samples/sample_3053.wav",
      "pitch": "C5",
      "loop_start": 0,
      "loop_end": 6590,
      "format": "16bit"
    },
    {
      "id": "stage2_5_s124",
      "wav": "audio/samples/sample_3054.wav",
      "pitch": "C5",
      "loop_start": 0,
      "loop_end": 6494,
      "format": "16bit"
    },
    {
      "id": "stage2_5_s125",
      "wav": "audio/samples/sample_3055.wav",
      "pitch": "C5",
      "loop_start": 0,
      "loop_end": 5332,
      "format": "16bit"
    },
    {
      "id": "stage2_5_s126",
      "wav": "audio/samples/sample_3056.wav",
      "pitch": "C5",
      "loop_start": 0,
      "loop_end": 6974,
      "format": "16bit"
    },
    {
      "id": "stage2_5_s127",
      "wav": "audio/samples/sample_3057.wav",
      "pitch": "C5",
      "loop_start": 0,
      "loop_end": 6910,
      "format": "16bit"
    },
    {
      "id": "stage2_5_s128",
      "wav": "audio/samples/sample_3058.wav",
      "pitch": "C5",
      "loop_start": 0,
      "loop_end": 6608,
      "format": "16bit"
    },
    {
      "id": "stage2_5_s129",
      "wav": "audio/samples/sample_3059.wav",
      "pitch": "C5",
      "loop_start": 0,
      "loop_end": 4987,
      "format": "16bit"
    },
    {
      "id": "stage2_5_s130",
      "wav": "audio/samples/sample_3060.wav",
      "pitch": "C5",
      "loop_start": 0,
      "loop_end": 6630,
      "format": "16bit"
    }
  ]
}